CDNDrivePro/__init__.py
CDNDrivePro/__main__.py
CDNDrivePro/util.py
CDNDrivePro/drivers/AliApi.py
CDNDrivePro/drivers/BaijiaApi.py
CDNDrivePro/drivers/BaseApi.py
CDNDrivePro/drivers/BiliApi.py
CDNDrivePro/drivers/CsdnApi.py
CDNDrivePro/drivers/JianApi.py
CDNDrivePro/drivers/NeteApi.py
CDNDrivePro/drivers/OscApi.py
CDNDrivePro/drivers/SogouApi.py
CDNDrivePro/drivers/SohuApi.py
CDNDrivePro/drivers/WeiboApi.py
CDNDrivePro/drivers/__init__.py
CDNDrivePro/encoders/GifEncoder.py
CDNDrivePro/encoders/JpgCatEncoder.py
CDNDrivePro/encoders/PngEncoder.py
CDNDrivePro/encoders/__init__.py
CDNDrivePro-2021.8.25.1.dist-info/LICENSE
CDNDrivePro-2021.8.25.1.dist-info/METADATA
CDNDrivePro-2021.8.25.1.dist-info/WHEEL
CDNDrivePro-2021.8.25.1.dist-info/entry_points.txt
CDNDrivePro-2021.8.25.1.dist-info/top_level.txt
CDNDrivePro-2021.8.25.1.dist-info/RECORD
