Metadata-Version: 2.1
Name: CDNDrivePro
Version: 2021.8.25.1
Summary: ☁️ CDNDrivePro，支持任意文件的全速上传与下载
Home-page: https://github.com/apachecn/CDNDrivePro
Author: dennischancs
Author-email: dennischanzh@gmail.com
License: UNKNOWN
Keywords: cdn,cloud,picbed,disk,drive,storage,pan,yun,网盘,图床,云
Platform: UNKNOWN
Classifier: Development Status :: 4 - Beta
Classifier: Environment :: Console
Classifier: Intended Audience :: Developers
Classifier: Intended Audience :: End Users/Desktop
Classifier: License :: Other/Proprietary License
Classifier: Natural Language :: Chinese (Simplified)
Classifier: Natural Language :: English
Classifier: Operating System :: OS Independent
Classifier: Programming Language :: Python :: 3
Classifier: Programming Language :: Python :: 3 :: Only
Classifier: Programming Language :: Python :: 3.6
Classifier: Programming Language :: Python :: 3.7
Classifier: Topic :: Communications :: File Sharing
Classifier: Topic :: Internet :: WWW/HTTP
Classifier: Topic :: Utilities
Requires-Python: >=3.6
License-File: LICENSE
Requires-Dist: requests
Requires-Dist: rsa
Requires-Dist: pillow
